setup.cfg
setup.py
twipy/__init__.py
twipy/adapter.py
twipy/api.py
twipy/capture.py
twipy/command.py
twipy/directory.py
twipy/keys.py
twipy/main.py
twipy/models.py
twipy.egg-info/PKG-INFO
twipy.egg-info/SOURCES.txt
twipy.egg-info/dependency_links.txt
twipy.egg-info/entry_points.txt
twipy.egg-info/requires.txt
twipy.egg-info/top_level.txt
twipy.egg-info/zip-safe