Metadata-Version: 1.1
Name: twipy
Version: 0.0.10
Summary: Another Twitter client using Python 2.7
Home-page: https://github.com/ervitis/twipy
Author: Victor Martin
Author-email: vitomarti@gmail.com
License: MIT
Download-URL: https://github.com/ervitis/twipy/tarball/0.0.10
Keywords: twitter client console
Platform: UNKNOWN
